djangocms_classic_admin_style/__init__.py
djangocms_classic_admin_style/static/djangocms_classic_admin_style/css/djangocms-classic-admin.css
djangocms_classic_admin_style/templates/admin/base_site.html
djangocms_classic_admin_style-1.0.2.dist-info/DESCRIPTION.rst
djangocms_classic_admin_style-1.0.2.dist-info/METADATA
djangocms_classic_admin_style-1.0.2.dist-info/RECORD
djangocms_classic_admin_style-1.0.2.dist-info/WHEEL
djangocms_classic_admin_style-1.0.2.dist-info/metadata.json
djangocms_classic_admin_style-1.0.2.dist-info/top_level.txt
