Metadata-Version: 2.0
Name: djangocms-classic-admin-style
Version: 1.0.2
Summary: Enables Django's original admin styling to work nicely with Django CMS
Home-page: https://github.com/tdsymonds/djangocms-classic-admin-style
Author: Tom Symonds
Author-email: tdsymonds@hotmail.com
License: MIT License
Keywords: djangocms-classic-admin-style,django,cms,admin,style
Platform: UNKNOWN
Classifier: Environment :: Web Environment
Classifier: Framework :: Django
Classifier: Framework :: Django :: 1.9
Classifier: Intended Audience :: Developers
Classifier: License :: OSI Approved :: MIT License
Classifier: Operating System :: OS Independent
Classifier: Programming Language :: Python :: 2
Classifier: Programming Language :: Python :: 2.7
Classifier: Topic :: Internet :: WWW/HTTP
Classifier: Topic :: Internet :: WWW/HTTP :: Dynamic Content
